mspiderx/__init__.py
mspiderx/info.py
mspiderx/shiti.py
mspiderx/sql.py
mspiderx/sx.py
mspiderx-1.9.3.dist-info/METADATA
mspiderx-1.9.3.dist-info/WHEEL
mspiderx-1.9.3.dist-info/top_level.txt
mspiderx-1.9.3.dist-info/RECORD
