Metadata-Version: 2.1
Name: mspiderx
Version: 1.9.3
Summary: mspiderx function
Home-page: https://pypi.org/project/mspiderx/
Author: wgnms
Author-email: wgnms@qq.com
License: https://pypi.org/project/mspiderx/
Platform: UNKNOWN
Requires-Python: >=3.6
Requires-Dist: requests (>=2.25.0)
Requires-Dist: lxml (>=4.6.0)
Requires-Dist: colorama (>=0.4.0)
Requires-Dist: rsa (>=4.7.0)
Requires-Dist: pycryptodome (>=3.10.0)
Requires-Dist: pyinstaller (>=4.5.0)
Requires-Dist: openpyxl (>=3.0.7)
Requires-Dist: js2py (>=0.71)
Requires-Dist: pyexecjs (>=1.5.1)
Requires-Dist: pillow (>=8.3.1)
Requires-Dist: pymysql (>=1.0.2)
Requires-Dist: chardet (<5.0.0,>=4.0.0)
Requires-Dist: loguru (>=0.6.0)
Requires-Dist: jsonpath (>=0.82)
Requires-Dist: pyserial (>=3.5)
Requires-Dist: uncurl (>=0.0.11)
Requires-Dist: ntplib (>=0.3.3)
Requires-Dist: xlrd (>=2.0.1)
